chatgpt_to_sqlite/__init__.py
chatgpt_to_sqlite/__main__.py
chatgpt_to_sqlite/cli.py
chatgpt_to_sqlite/utils.py
chatgpt_to_sqlite-1.0.0.dist-info/WHEEL
chatgpt_to_sqlite-1.0.0.dist-info/entry_points.txt
chatgpt_to_sqlite-1.0.0.dist-info/METADATA
chatgpt_to_sqlite-1.0.0.dist-info/RECORD
