Metadata-Version: 2.3
Name: chatgpt-to-sqlite
Version: 1.0.0
Summary: Import ChatGPT conversations into a SQLite database
Author: Scott Carvalho
License: Apache-2.0
Classifier: License :: OSI Approved :: Apache Software License
Requires-Dist: click
Requires-Dist: sqlite-utils
Requires-Dist: funcy
Requires-Python: >=3.10
Project-URL: CI, https://github.com/Scarvy/chatgpt-to-sqlite/actions
Project-URL: Changelog, https://github.com/Scarvy/chatgpt-to-sqlite/releases
Project-URL: Homepage, https://github.com/Scarvy/chatgpt-to-sqlite
Project-URL: Issues, https://github.com/Scarvy/chatgpt-to-sqlite/issues
